fscm/__init__.py
fscm/changes.py
fscm/fscm.py
fscm/py.typed
fscm/remote.py
fscm/remote_cli.py
fscm/secrets.py
fscm/contrib/__init__.py
fscm/contrib/python.py
fscm/modules/__init__.py
fscm/modules/docker.py
fscm/modules/jinja.py
fscm/modules/pki.py
fscm/modules/systemd.py
fscm/modules/wireguard.py
fscm/modules/files/wg-updown.tmpl.sh
fscm/thirdparty/__init__.py
fscm/thirdparty/color.py
fscm-0.0.6.dist-info/licenses/LICENSE
fscm-0.0.6.dist-info/METADATA
fscm-0.0.6.dist-info/WHEEL
fscm-0.0.6.dist-info/entry_points.txt
fscm-0.0.6.dist-info/top_level.txt
fscm-0.0.6.dist-info/RECORD
