Metadata-Version: 2.4
Name: fscm
Version: 0.0.6
Summary: Finally, simple configuration management!
License: MIT License
Classifier: Programming Language :: Python :: 3
Requires-Python: >=3.10
License-File: LICENSE
Requires-Dist: importlib-metadata; python_version < "3.10"
Requires-Dist: jinja2>=3.1
Provides-Extra: remote
Requires-Dist: mitogen-plus>=1.0.0; extra == "remote"
Requires-Dist: clii>=1.0.0; extra == "remote"
Requires-Dist: pyyaml; extra == "remote"
Provides-Extra: pki
Requires-Dist: cryptography; extra == "pki"
Dynamic: license-file
